MANIFEST.in
NEWS.rst
README.rst
setup.py
djvasa/__init__.py
djvasa/main.py
djvasa/tests.py
djvasa.egg-info/PKG-INFO
djvasa.egg-info/SOURCES.txt
djvasa.egg-info/dependency_links.txt
djvasa.egg-info/entry_points.txt
djvasa.egg-info/requires.txt
djvasa.egg-info/top_level.txt
djvasa/templates/__init__.py
djvasa/templates/base.mustache
djvasa/templates/gitignore.mustache
djvasa/templates/hgignore.mustache
djvasa/templates/manage.mustache
djvasa/templates/minion.mustache
djvasa/templates/motd.mustache
djvasa/templates/mysql.mustache
djvasa/templates/pgconf.mustache
djvasa/templates/pillar_settings.mustache
djvasa/templates/pillar_top.mustache
djvasa/templates/pip_requirements.mustache
djvasa/templates/postgres.mustache
djvasa/templates/procfile.mustache
djvasa/templates/requirements.mustache
djvasa/templates/salt_project.mustache
djvasa/templates/settings.mustache
djvasa/templates/settings_local.mustache
djvasa/templates/top.mustache
djvasa/templates/urls.mustache
djvasa/templates/vagrantfile.mustache
djvasa/templates/wsgi.mustache