Metadata-Version: 1.1
Name: djvasa
Version: 0.1.1
Summary: Initialize a new Django project with Vagrant for easy start
Home-page: https://github.com/cgallemore/djvasa
Author: Chad Gallemore
Author-email: cgallemore@gmail.com
License: MIT
Keywords: terminal django vagrant saltstack cli
Platform: UNKNOWN
Classifier: Development Status :: 4 - Beta
Classifier: Environment :: Console
Classifier: Framework :: Django
Classifier: Intended Audience :: Developers
Classifier: Natural Language :: English
Classifier: License :: OSI Approved :: MIT License
Classifier: Programming Language :: Python :: 2.6
Classifier: Programming Language :: Python :: 2.7
Classifier: Topic :: Software Development
